dryerlint.py
dryerlint-1.0.0.dist-info/licenses/LICENSE
dryerlint-1.0.0.dist-info/METADATA
dryerlint-1.0.0.dist-info/WHEEL
dryerlint-1.0.0.dist-info/entry_points.txt
dryerlint-1.0.0.dist-info/top_level.txt
dryerlint-1.0.0.dist-info/RECORD
