Metadata-Version: 2.4
Name: dryerlint
Version: 1.0.0
Summary: 🧺 DryerLint - Remove the Fuzz. A Python-powered code quality and linting tool.
Author: Charlie
License: MIT
Classifier: Programming Language :: Python :: 3
Classifier: License :: OSI Approved :: MIT License
License-File: LICENSE
Dynamic: author
Dynamic: classifier
Dynamic: description
Dynamic: description-content-type
Dynamic: license
Dynamic: license-file
Dynamic: summary
